zvtk/__init__.py
zvtk/zvtk.py
zvtk-0.1.1.dist-info/licenses/LICENSE
zvtk-0.1.1.dist-info/WHEEL
zvtk-0.1.1.dist-info/METADATA
zvtk-0.1.1.dist-info/RECORD
