Metadata-Version: 2.4
Name: zvtk
Version: 0.1.1
Summary: VTK zstandard compression library.
Author-email: The PyVista developers <info@pyvista.org>
License-Expression: MIT
Classifier: Development Status :: 4 - Beta
Classifier: Intended Audience :: Developers
Classifier: Operating System :: OS Independent
Classifier: Programming Language :: Python :: 3.10
Classifier: Programming Language :: Python :: 3.11
Classifier: Programming Language :: Python :: 3.12
Classifier: Programming Language :: Python :: 3.13
License-File: LICENSE
Requires-Dist: pyvista>=0.45.0
Requires-Dist: tqdm>=4.0.0
Requires-Dist: vtk>=9.4.0
Requires-Dist: zstandard>=0.24.0
Requires-Dist: numpydoc==1.9.0 ; extra == "docs"
Requires-Dist: sphinx-book-theme==1.1.4 ; extra == "docs"
Requires-Dist: sphinx-copybutton==0.5.2 ; extra == "docs"
Requires-Dist: sphinx-gallery==0.19.0 ; extra == "docs"
Requires-Dist: sphinx-notfound-page==1.1.0 ; extra == "docs"
Requires-Dist: sphinx==8.2.1 ; extra == "docs"
Requires-Dist: pytest-cov==7.0.0 ; extra == "tests"
Requires-Dist: pytest>=6.2.0 ; extra == "tests"
Project-URL: Home, https://github.com/pyvista/zvtk
Provides-Extra: docs
Provides-Extra: tests
